Ryzenth/__init__.py
Ryzenth/__version__.py
Ryzenth/_asynchisded.py
Ryzenth/_base_client.py
Ryzenth/_benchmark.py
Ryzenth/_client.py
Ryzenth/_errors.py
Ryzenth/_export_class.py
Ryzenth/_new_client.py
Ryzenth/_shared.py
Ryzenth/_synchisded.py
Ryzenth/_callbody/__init__.py
Ryzenth/_callbody/_call_image_gemini_edit.py
Ryzenth/_callbody/_call_image_ghibli.py
Ryzenth/_callbody/_call_image_openai.py
Ryzenth/_callbody/_call_image_turntext_gemini.py
Ryzenth/_callbody/_call_image_vision.py
Ryzenth/enums/__init__.py
Ryzenth/enums/types.py
Ryzenth/helper/__init__.py
Ryzenth/helper/_decorators.py
Ryzenth/helper/_federation.py
Ryzenth/helper/_fonts.py
Ryzenth/helper/_images.py
Ryzenth/helper/_moderator.py
Ryzenth/helper/_openai.py
Ryzenth/helper/_ryzenth.py
Ryzenth/helper/_thinking.py
Ryzenth/mongo/__init__.py
Ryzenth/mongo/_chats_conversation.py
Ryzenth/new_helper/__init__.py
Ryzenth/new_helper/_claude_chats.py
Ryzenth/new_helper/_cohere_chats.py
Ryzenth/new_helper/_deepseek_chats.py
Ryzenth/new_helper/_default_chats.py
Ryzenth/new_helper/_default_images.py
Ryzenth/new_helper/_flux_images.py
Ryzenth/new_helper/_gemini_chats.py
Ryzenth/new_helper/_grok_chats.py
Ryzenth/new_helper/_huggingface_chats.py
Ryzenth/new_helper/_models.py
Ryzenth/new_helper/_old_gemini_chats.py
Ryzenth/new_helper/_openai_chats.py
Ryzenth/new_helper/_openai_images.py
Ryzenth/new_helper/_qwen_chats.py
Ryzenth/new_helper/_qwen_images.py
Ryzenth/new_helper/_qwen_videos.py
Ryzenth/new_helper/_zai_chats.py
Ryzenth/pyoraddons/__init__.py
Ryzenth/tests/__init__.py
Ryzenth/tests/test_deepseek.py
Ryzenth/tests/test_moderator.py
Ryzenth/tests/test_ryzenthapiclient.py
Ryzenth/tests/test_send.py
Ryzenth/tests/test_send_downloader.py
Ryzenth/tl/__init__.py
Ryzenth/tl/logger_service.py
Ryzenth/tool/__init__.py
Ryzenth/tool/alibaba.py
Ryzenth/tool/claude.py
Ryzenth/tool/cloudflare.py
Ryzenth/tool/cohere.py
Ryzenth/tool/deepseek.py
Ryzenth/tool/exonity.py
Ryzenth/tool/fgsi.py
Ryzenth/tool/grok.py
Ryzenth/tool/itzpire.py
ryzenth-2.4.3.dist-info/licenses/LICENSE
ryzenth-2.4.3.dist-info/METADATA
ryzenth-2.4.3.dist-info/WHEEL
ryzenth-2.4.3.dist-info/top_level.txt
ryzenth-2.4.3.dist-info/RECORD
