Metadata-Version: 2.4
Name: Ryzenth
Version: 2.4.3
Summary: Ryzenth is a flexible Multi-API SDK with built-in support for API key management and database integration.
Author: TeamKillerX
License: MIT
Project-URL: Source, https://github.com/TeamKillerX/Ryzenth/
Project-URL: Issues, https://github.com/TeamKillerX/Ryzenth/discussions
Keywords: Multi-API,Ryzenth-SDK,Ryzenth
Classifier: Programming Language :: Python :: 3
Classifier: Programming Language :: Python :: 3.7
Classifier: Programming Language :: Python :: 3.8
Classifier: Programming Language :: Python :: 3.9
Classifier: Programming Language :: Python :: 3.10
Classifier: Programming Language :: Python :: 3.11
Classifier: Development Status :: 5 - Production/Stable
Classifier: License :: OSI Approved :: MIT License
Classifier: Operating System :: OS Independent
Classifier: Intended Audience :: Developers
Classifier: Natural Language :: English
Requires-Python: ~=3.7
License-File: LICENSE
Requires-Dist: requests
Requires-Dist: pydantic
Requires-Dist: typing
Requires-Dist: aiohttp
Requires-Dist: motor
Requires-Dist: httpx[http2]
Requires-Dist: bs4
Requires-Dist: python-box
Provides-Extra: fast
Requires-Dist: aiohttp; extra == "fast"
Requires-Dist: motor; extra == "fast"
Requires-Dist: wget; extra == "fast"
Requires-Dist: requests; extra == "fast"
Requires-Dist: httpx[http2]; extra == "fast"
Requires-Dist: python-box; extra == "fast"
Requires-Dist: pydantic; extra == "fast"
Requires-Dist: bs4; extra == "fast"
Requires-Dist: typing; extra == "fast"
Dynamic: author
Dynamic: classifier
Dynamic: description
Dynamic: description-content-type
Dynamic: keywords
Dynamic: license
Dynamic: license-file
Dynamic: project-url
Dynamic: provides-extra
Dynamic: requires-dist
Dynamic: requires-python
Dynamic: summary
